carson/LICENSE
carson/__init__.py
carson/__main__.py
carson/core.py
carson/endpoints.py
carson/logging.py
carson/stream.py
carson/tokens.py
carson/utils.py
carson/plat/Windows.py
carson/plat/__init__.py
carson-1.2.4.dist-info/METADATA
carson-1.2.4.dist-info/WHEEL
carson-1.2.4.dist-info/entry_points.txt
carson-1.2.4.dist-info/top_level.txt
carson-1.2.4.dist-info/RECORD
