Metadata-Version: 2.1
Name: carson
Version: 1.2.4
Summary: Version=1.2.4+eb347f3  Description=An asyncio package to interact with the Tesla JSON web service.
Author-email: Michael Loyd <michael@loyd.org>
License: MIT
Project-URL: url, https://github.com/mloyd/carson
Keywords: tesla,asyncio,json
Classifier: Development Status :: 5 - Production/Stable
Classifier: Intended Audience :: Developers
Classifier: Topic :: Software Development :: Libraries
Classifier: Topic :: Software Development :: Libraries :: Python Modules
Classifier: License :: OSI Approved :: MIT License
Classifier: Programming Language :: Python :: 3
Requires-Python: >=3.8
Requires-Dist: aiohttp
Provides-Extra: jwt
Requires-Dist: pyjwt ; extra == 'jwt'
Requires-Dist: cryptography ; extra == 'jwt'
